scm_python_host/lib/hosts.py
scm_python_host-0.1.1.dist-info/METADATA
scm_python_host-0.1.1.dist-info/WHEEL
scm_python_host-0.1.1.dist-info/top_level.txt
scm_python_host-0.1.1.dist-info/RECORD
