Metadata-Version: 2.4
Name: scm-python-host
Version: 0.1.1
Summary: An windows host plugin Python project to use cli manage it
Author-email: "Shao,ShunZhong" <tempestwin@163.com>
Requires-Python: >=3.9
Requires-Dist: requests>=2.31
Provides-Extra: dev
Requires-Dist: pytest>=8.0; extra == "dev"
Requires-Dist: pytest-cov; extra == "dev"
Requires-Dist: ruff; extra == "dev"
Requires-Dist: black; extra == "dev"
